setup.py
vishnuvardhan_dist/Binomialdistribution.py
vishnuvardhan_dist/Gaussiandistribution.py
vishnuvardhan_dist/Generaldistribution.py
vishnuvardhan_dist/__init__.py
vishnuvardhan_dist.egg-info/PKG-INFO
vishnuvardhan_dist.egg-info/SOURCES.txt
vishnuvardhan_dist.egg-info/dependency_links.txt
vishnuvardhan_dist.egg-info/not-zip-safe
vishnuvardhan_dist.egg-info/top_level.txt